{"merge_info": [1, -1, 0, -1], "bbox_info": [0, 0, 25, 7]}
{"merge_info": [1, -1, 1, -1], "bbox_info": [216, 0, 236, 7]}
{"merge_info": [2, -1, 1, -1], "bbox_info": [79, 10, 110, 17]}
{"merge_info": [2, -1, 2, -1], "bbox_info": [135, 10, 165, 17]}
{"merge_info": [2, -1, 3, -1], "bbox_info": [190, 10, 220, 17]}
{"merge_info": [2, -1, 4, -1], "bbox_info": [245, 10, 275, 17]}
{"merge_info": [2, -1, 5, -1], "bbox_info": [300, 10, 330, 17]}
{"merge_info": [2, -1, 6, -1], "bbox_info": [361, 10, 386, 17]}
{"merge_info": [3, -1, 0, -1], "bbox_info": [0, 24, 38, 31]}
{"merge_info": [3, -1, 1, -1], "bbox_info": [97, 24, 110, 31]}
{"merge_info": [3, -1, 2, -1], "bbox_info": [153, 24, 165, 31]}
{"merge_info": [3, -1, 3, -1], "bbox_info": [208, 24, 220, 31]}
{"merge_info": [3, -1, 4, -1], "bbox_info": [263, 24, 275, 31]}
{"merge_info": [3, -1, 5, -1], "bbox_info": [318, 24, 330, 31]}
{"merge_info": [3, -1, 6, -1], "bbox_info": [373, 24, 386, 31]}
{"merge_info": [4, -1, 0, -1], "bbox_info": [0, 33, 47, 40]}
{"merge_info": [4, -1, 1, -1], "bbox_info": [97, 33, 110, 40]}
{"merge_info": [4, -1, 2, -1], "bbox_info": [153, 33, 165, 40]}
{"merge_info": [4, -1, 3, -1], "bbox_info": [208, 33, 220, 40]}
{"merge_info": [4, -1, 4, -1], "bbox_info": [263, 33, 275, 40]}
{"merge_info": [4, -1, 5, -1], "bbox_info": [318, 33, 330, 40]}
{"merge_info": [4, -1, 6, -1], "bbox_info": [373, 33, 386, 40]}
{"merge_info": [5, -1, 0, -1], "bbox_info": [0, 42, 17, 49]}
{"merge_info": [5, -1, 1, -1], "bbox_info": [101, 42, 110, 49]}
{"merge_info": [5, -1, 2, -1], "bbox_info": [156, 42, 165, 49]}
{"merge_info": [5, -1, 3, -1], "bbox_info": [211, 42, 220, 49]}
{"merge_info": [5, -1, 4, -1], "bbox_info": [263, 42, 275, 49]}
{"merge_info": [5, -1, 5, -1], "bbox_info": [318, 42, 330, 49]}
{"merge_info": [5, -1, 6, -1], "bbox_info": [377, 42, 386, 49]}
{"merge_info": [6, -1, 0, -1], "bbox_info": [0, 51, 16, 58]}
{"merge_info": [6, -1, 1, -1], "bbox_info": [101, 51, 110, 58]}
{"merge_info": [6, -1, 2, -1], "bbox_info": [156, 51, 165, 58]}
{"merge_info": [6, -1, 3, -1], "bbox_info": [211, 51, 220, 58]}
{"merge_info": [6, -1, 4, -1], "bbox_info": [266, 51, 275, 58]}
{"merge_info": [6, -1, 5, -1], "bbox_info": [322, 51, 330, 58]}
{"merge_info": [6, -1, 6, -1], "bbox_info": [377, 51, 386, 58]}
{"merge_info": [7, -1, 0, -1], "bbox_info": [0, 60, 33, 67]}
{"merge_info": [7, -1, 1, -1], "bbox_info": [101, 60, 110, 67]}
{"merge_info": [7, -1, 2, -1], "bbox_info": [156, 60, 165, 67]}
{"merge_info": [7, -1, 3, -1], "bbox_info": [211, 60, 220, 67]}
{"merge_info": [7, -1, 4, -1], "bbox_info": [266, 60, 275, 67]}
{"merge_info": [7, -1, 5, -1], "bbox_info": [322, 60, 330, 67]}
{"merge_info": [7, -1, 6, -1], "bbox_info": [377, 60, 386, 67]}
{"merge_info": [8, -1, 0, -1], "bbox_info": [0, 69, 22, 76]}
{"merge_info": [8, -1, 1, -1], "bbox_info": [101, 69, 110, 76]}
{"merge_info": [8, -1, 2, -1], "bbox_info": [156, 69, 165, 76]}
{"merge_info": [8, -1, 3, -1], "bbox_info": [211, 69, 220, 76]}
{"merge_info": [8, -1, 4, -1], "bbox_info": [266, 69, 275, 76]}
{"merge_info": [8, -1, 5, -1], "bbox_info": [322, 69, 330, 76]}
{"merge_info": [8, -1, 6, -1], "bbox_info": [377, 69, 386, 76]}
{"merge_info": [9, -1, 0, -1], "bbox_info": [0, 78, 19, 85]}
{"merge_info": [9, -1, 1, -1], "bbox_info": [101, 78, 110, 85]}
{"merge_info": [9, -1, 2, -1], "bbox_info": [156, 78, 165, 85]}
{"merge_info": [9, -1, 3, -1], "bbox_info": [211, 78, 220, 85]}
{"merge_info": [9, -1, 4, -1], "bbox_info": [266, 78, 275, 85]}
{"merge_info": [9, -1, 5, -1], "bbox_info": [322, 78, 330, 85]}
{"merge_info": [9, -1, 6, -1], "bbox_info": [377, 78, 386, 85]}
{"merge_info": [10, -1, 0, -1], "bbox_info": [0, 87, 45, 94]}
{"merge_info": [10, -1, 1, -1], "bbox_info": [101, 87, 110, 94]}
{"merge_info": [10, -1, 2, -1], "bbox_info": [156, 87, 165, 94]}
{"merge_info": [10, -1, 3, -1], "bbox_info": [211, 87, 220, 94]}
{"merge_info": [10, -1, 4, -1], "bbox_info": [266, 87, 275, 94]}
{"merge_info": [10, -1, 5, -1], "bbox_info": [322, 87, 330, 94]}
{"merge_info": [10, -1, 6, -1], "bbox_info": [377, 87, 386, 94]}
{"merge_info": [11, -1, 0, -1], "bbox_info": [0, 97, 17, 104]}
{"merge_info": [11, -1, 1, -1], "bbox_info": [101, 97, 110, 104]}
{"merge_info": [11, -1, 2, -1], "bbox_info": [156, 97, 165, 104]}
{"merge_info": [11, -1, 3, -1], "bbox_info": [211, 97, 220, 104]}
{"merge_info": [11, -1, 4, -1], "bbox_info": [266, 97, 275, 104]}
{"merge_info": [11, -1, 5, -1], "bbox_info": [322, 97, 330, 104]}
{"merge_info": [11, -1, 6, -1], "bbox_info": [377, 97, 386, 104]}
{"merge_info": [12, -1, 0, -1], "bbox_info": [0, 106, 20, 113]}
{"merge_info": [12, -1, 1, -1], "bbox_info": [101, 106, 110, 113]}
{"merge_info": [12, -1, 2, -1], "bbox_info": [156, 106, 165, 113]}
{"merge_info": [12, -1, 3, -1], "bbox_info": [211, 106, 220, 113]}
{"merge_info": [12, -1, 4, -1], "bbox_info": [266, 106, 275, 113]}
{"merge_info": [12, -1, 5, -1], "bbox_info": [322, 106, 330, 113]}
{"merge_info": [12, -1, 6, -1], "bbox_info": [377, 106, 386, 113]}
{"merge_info": [13, -1, 0, -1], "bbox_info": [0, 115, 19, 122]}
{"merge_info": [13, -1, 1, -1], "bbox_info": [101, 115, 110, 122]}
{"merge_info": [13, -1, 2, -1], "bbox_info": [156, 115, 165, 122]}
{"merge_info": [13, -1, 3, -1], "bbox_info": [211, 115, 220, 122]}
{"merge_info": [13, -1, 4, -1], "bbox_info": [266, 115, 275, 122]}
{"merge_info": [13, -1, 5, -1], "bbox_info": [322, 115, 330, 122]}
{"merge_info": [13, -1, 6, -1], "bbox_info": [377, 115, 386, 122]}
{"merge_info": [14, -1, 0, -1], "bbox_info": [0, 124, 26, 131]}
{"merge_info": [14, -1, 1, -1], "bbox_info": [101, 124, 110, 131]}
{"merge_info": [14, -1, 2, -1], "bbox_info": [156, 124, 165, 131]}
{"merge_info": [14, -1, 3, -1], "bbox_info": [211, 124, 220, 131]}
{"merge_info": [14, -1, 4, -1], "bbox_info": [266, 124, 275, 131]}
{"merge_info": [14, -1, 5, -1], "bbox_info": [322, 124, 330, 131]}
{"merge_info": [14, -1, 6, -1], "bbox_info": [377, 124, 386, 131]}
{"merge_info": [15, -1, 0, -1], "bbox_info": [0, 133, 25, 140]}
{"merge_info": [15, -1, 1, -1], "bbox_info": [101, 133, 110, 140]}
{"merge_info": [15, -1, 2, -1], "bbox_info": [156, 133, 165, 140]}
{"merge_info": [15, -1, 3, -1], "bbox_info": [211, 133, 220, 140]}
{"merge_info": [15, -1, 4, -1], "bbox_info": [266, 133, 275, 140]}
{"merge_info": [15, -1, 5, -1], "bbox_info": [322, 133, 330, 140]}
{"merge_info": [15, -1, 6, -1], "bbox_info": [377, 133, 386, 140]}
{"merge_info": [16, -1, 0, -1], "bbox_info": [0, 142, 21, 149]}
{"merge_info": [16, -1, 1, -1], "bbox_info": [101, 142, 110, 149]}
{"merge_info": [16, -1, 2, -1], "bbox_info": [156, 142, 165, 149]}
{"merge_info": [16, -1, 3, -1], "bbox_info": [211, 142, 220, 149]}
{"merge_info": [16, -1, 4, -1], "bbox_info": [266, 142, 275, 149]}
{"merge_info": [16, -1, 5, -1], "bbox_info": [322, 142, 330, 149]}
{"merge_info": [16, -1, 6, -1], "bbox_info": [377, 142, 386, 149]}
{"merge_info": [17, -1, 0, -1], "bbox_info": [0, 151, 14, 158]}
{"merge_info": [17, -1, 1, -1], "bbox_info": [101, 151, 110, 158]}
{"merge_info": [17, -1, 2, -1], "bbox_info": [156, 151, 165, 158]}
{"merge_info": [17, -1, 3, -1], "bbox_info": [211, 151, 220, 158]}
{"merge_info": [17, -1, 4, -1], "bbox_info": [266, 151, 275, 158]}
{"merge_info": [17, -1, 5, -1], "bbox_info": [322, 151, 330, 158]}
{"merge_info": [17, -1, 6, -1], "bbox_info": [377, 151, 386, 158]}
{"merge_info": [18, -1, 0, -1], "bbox_info": [0, 160, 33, 167]}
{"merge_info": [18, -1, 1, -1], "bbox_info": [101, 160, 110, 167]}
{"merge_info": [18, -1, 2, -1], "bbox_info": [156, 160, 165, 167]}
{"merge_info": [18, -1, 3, -1], "bbox_info": [211, 160, 220, 167]}
{"merge_info": [18, -1, 4, -1], "bbox_info": [266, 160, 275, 167]}
{"merge_info": [18, -1, 5, -1], "bbox_info": [322, 160, 330, 167]}
{"merge_info": [18, -1, 6, -1], "bbox_info": [377, 160, 386, 167]}
{"merge_info": [19, -1, 0, -1], "bbox_info": [0, 169, 21, 176]}
{"merge_info": [19, -1, 1, -1], "bbox_info": [101, 169, 110, 176]}
{"merge_info": [19, -1, 2, -1], "bbox_info": [156, 169, 165, 176]}
{"merge_info": [19, -1, 3, -1], "bbox_info": [211, 169, 220, 176]}
{"merge_info": [19, -1, 4, -1], "bbox_info": [266, 169, 275, 176]}
{"merge_info": [19, -1, 5, -1], "bbox_info": [322, 169, 330, 176]}
{"merge_info": [19, -1, 6, -1], "bbox_info": [377, 169, 386, 176]}
{"merge_info": [20, -1, 0, -1], "bbox_info": [0, 179, 28, 186]}
{"merge_info": [20, -1, 1, -1], "bbox_info": [101, 179, 110, 186]}
{"merge_info": [20, -1, 2, -1], "bbox_info": [156, 179, 165, 186]}
{"merge_info": [20, -1, 3, -1], "bbox_info": [211, 179, 220, 186]}
{"merge_info": [20, -1, 4, -1], "bbox_info": [266, 179, 275, 186]}
{"merge_info": [20, -1, 5, -1], "bbox_info": [322, 179, 330, 186]}
{"merge_info": [20, -1, 6, -1], "bbox_info": [377, 179, 386, 186]}
{"merge_info": [21, -1, 0, -1], "bbox_info": [0, 188, 17, 195]}
{"merge_info": [21, -1, 1, -1], "bbox_info": [101, 188, 110, 195]}
{"merge_info": [21, -1, 2, -1], "bbox_info": [156, 188, 165, 195]}
{"merge_info": [21, -1, 3, -1], "bbox_info": [211, 188, 220, 195]}
{"merge_info": [21, -1, 4, -1], "bbox_info": [266, 188, 275, 195]}
{"merge_info": [21, -1, 5, -1], "bbox_info": [322, 188, 330, 195]}
{"merge_info": [21, -1, 6, -1], "bbox_info": [377, 188, 386, 195]}
{"merge_info": [22, -1, 0, -1], "bbox_info": [0, 197, 21, 204]}
{"merge_info": [22, -1, 1, -1], "bbox_info": [101, 197, 110, 204]}
{"merge_info": [22, -1, 2, -1], "bbox_info": [156, 197, 165, 204]}
{"merge_info": [22, -1, 3, -1], "bbox_info": [211, 197, 220, 204]}
{"merge_info": [22, -1, 4, -1], "bbox_info": [266, 197, 275, 204]}
{"merge_info": [22, -1, 5, -1], "bbox_info": [322, 197, 330, 204]}
{"merge_info": [22, -1, 6, -1], "bbox_info": [377, 197, 386, 204]}
{"merge_info": [23, -1, 0, -1], "bbox_info": [0, 206, 26, 213]}
{"merge_info": [23, -1, 1, -1], "bbox_info": [101, 206, 110, 213]}
{"merge_info": [23, -1, 2, -1], "bbox_info": [156, 206, 165, 213]}
{"merge_info": [23, -1, 3, -1], "bbox_info": [211, 206, 220, 213]}
{"merge_info": [23, -1, 4, -1], "bbox_info": [266, 206, 275, 213]}
{"merge_info": [23, -1, 5, -1], "bbox_info": [322, 206, 330, 213]}
{"merge_info": [23, -1, 6, -1], "bbox_info": [377, 206, 386, 213]}
{"merge_info": [24, -1, 0, -1], "bbox_info": [0, 215, 23, 222]}
{"merge_info": [24, -1, 1, -1], "bbox_info": [101, 215, 110, 222]}
{"merge_info": [24, -1, 2, -1], "bbox_info": [156, 215, 165, 222]}
{"merge_info": [24, -1, 3, -1], "bbox_info": [211, 215, 220, 222]}
{"merge_info": [24, -1, 4, -1], "bbox_info": [266, 215, 275, 222]}
{"merge_info": [24, -1, 5, -1], "bbox_info": [322, 215, 330, 222]}
{"merge_info": [24, -1, 6, -1], "bbox_info": [377, 215, 386, 222]}
{"merge_info": [25, -1, 0, -1], "bbox_info": [0, 224, 25, 231]}
{"merge_info": [25, -1, 1, -1], "bbox_info": [101, 224, 110, 231]}
{"merge_info": [25, -1, 2, -1], "bbox_info": [156, 224, 165, 231]}
{"merge_info": [25, -1, 3, -1], "bbox_info": [211, 224, 220, 231]}
{"merge_info": [25, -1, 4, -1], "bbox_info": [266, 224, 275, 231]}
{"merge_info": [25, -1, 5, -1], "bbox_info": [322, 224, 330, 231]}
{"merge_info": [25, -1, 6, -1], "bbox_info": [377, 224, 386, 231]}
{"merge_info": [26, -1, 0, -1], "bbox_info": [0, 233, 25, 240]}
{"merge_info": [26, -1, 1, -1], "bbox_info": [101, 233, 110, 240]}
{"merge_info": [26, -1, 2, -1], "bbox_info": [156, 233, 165, 240]}
{"merge_info": [26, -1, 3, -1], "bbox_info": [211, 233, 220, 240]}
{"merge_info": [26, -1, 4, -1], "bbox_info": [266, 233, 275, 240]}
{"merge_info": [26, -1, 5, -1], "bbox_info": [322, 233, 330, 240]}
{"merge_info": [26, -1, 6, -1], "bbox_info": [377, 233, 386, 240]}
{"merge_info": [27, -1, 0, -1], "bbox_info": [0, 242, 36, 249]}
{"merge_info": [27, -1, 1, -1], "bbox_info": [101, 242, 110, 249]}
{"merge_info": [27, -1, 2, -1], "bbox_info": [156, 242, 165, 249]}
{"merge_info": [27, -1, 3, -1], "bbox_info": [211, 242, 220, 249]}
{"merge_info": [27, -1, 4, -1], "bbox_info": [266, 242, 275, 249]}
{"merge_info": [27, -1, 5, -1], "bbox_info": [322, 242, 330, 249]}
{"merge_info": [27, -1, 6, -1], "bbox_info": [377, 242, 386, 249]}
{"merge_info": [28, -1, 0, -1], "bbox_info": [0, 251, 16, 258]}
{"merge_info": [28, -1, 1, -1], "bbox_info": [101, 251, 110, 258]}
{"merge_info": [28, -1, 2, -1], "bbox_info": [156, 251, 165, 258]}
{"merge_info": [28, -1, 3, -1], "bbox_info": [211, 251, 220, 258]}
{"merge_info": [28, -1, 4, -1], "bbox_info": [266, 251, 275, 258]}
{"merge_info": [28, -1, 5, -1], "bbox_info": [322, 251, 330, 258]}
{"merge_info": [28, -1, 6, -1], "bbox_info": [377, 251, 386, 258]}
{"merge_info": [29, -1, 0, -1], "bbox_info": [0, 260, 26, 267]}
{"merge_info": [29, -1, 1, -1], "bbox_info": [101, 260, 110, 267]}
{"merge_info": [29, -1, 2, -1], "bbox_info": [156, 260, 165, 267]}
{"merge_info": [29, -1, 3, -1], "bbox_info": [211, 260, 220, 267]}
{"merge_info": [29, -1, 4, -1], "bbox_info": [266, 260, 275, 267]}
{"merge_info": [29, -1, 5, -1], "bbox_info": [322, 260, 330, 267]}
{"merge_info": [29, -1, 6, -1], "bbox_info": [377, 260, 386, 267]}
{"merge_info": [30, -1, 0, -1], "bbox_info": [0, 270, 27, 277]}
{"merge_info": [30, -1, 1, -1], "bbox_info": [101, 270, 110, 277]}
{"merge_info": [30, -1, 2, -1], "bbox_info": [156, 270, 165, 277]}
{"merge_info": [30, -1, 3, -1], "bbox_info": [211, 270, 220, 277]}
{"merge_info": [30, -1, 4, -1], "bbox_info": [266, 270, 275, 277]}
{"merge_info": [30, -1, 5, -1], "bbox_info": [322, 270, 330, 277]}
{"merge_info": [30, -1, 6, -1], "bbox_info": [377, 270, 386, 277]}
{"merge_info": [31, -1, 0, -1], "bbox_info": [0, 279, 25, 286]}
{"merge_info": [31, -1, 1, -1], "bbox_info": [101, 279, 110, 286]}
{"merge_info": [31, -1, 2, -1], "bbox_info": [156, 279, 165, 286]}
{"merge_info": [31, -1, 3, -1], "bbox_info": [211, 279, 220, 286]}
{"merge_info": [31, -1, 4, -1], "bbox_info": [266, 279, 275, 286]}
{"merge_info": [31, -1, 5, -1], "bbox_info": [322, 279, 330, 286]}
{"merge_info": [31, -1, 6, -1], "bbox_info": [377, 279, 386, 286]}
{"merge_info": [32, -1, 0, -1], "bbox_info": [0, 288, 21, 295]}
{"merge_info": [32, -1, 1, -1], "bbox_info": [101, 288, 110, 295]}
{"merge_info": [32, -1, 2, -1], "bbox_info": [156, 288, 165, 295]}
{"merge_info": [32, -1, 3, -1], "bbox_info": [211, 288, 220, 295]}
{"merge_info": [32, -1, 4, -1], "bbox_info": [266, 288, 275, 295]}
{"merge_info": [32, -1, 5, -1], "bbox_info": [322, 288, 330, 295]}
{"merge_info": [32, -1, 6, -1], "bbox_info": [377, 288, 386, 295]}
{"merge_info": [33, -1, 0, -1], "bbox_info": [0, 297, 32, 304]}
{"merge_info": [33, -1, 1, -1], "bbox_info": [101, 297, 110, 304]}
{"merge_info": [33, -1, 2, -1], "bbox_info": [156, 297, 165, 304]}
{"merge_info": [33, -1, 3, -1], "bbox_info": [211, 297, 220, 304]}
{"merge_info": [33, -1, 4, -1], "bbox_info": [266, 297, 275, 304]}
{"merge_info": [33, -1, 5, -1], "bbox_info": [322, 297, 330, 304]}
{"merge_info": [33, -1, 6, -1], "bbox_info": [377, 297, 386, 304]}
{"merge_info": [34, -1, 0, -1], "bbox_info": [0, 306, 24, 313]}
{"merge_info": [34, -1, 1, -1], "bbox_info": [101, 306, 110, 313]}
{"merge_info": [34, -1, 2, -1], "bbox_info": [156, 306, 165, 313]}
{"merge_info": [34, -1, 3, -1], "bbox_info": [211, 306, 220, 313]}
{"merge_info": [34, -1, 4, -1], "bbox_info": [266, 306, 275, 313]}
{"merge_info": [34, -1, 5, -1], "bbox_info": [322, 306, 330, 313]}
{"merge_info": [34, -1, 6, -1], "bbox_info": [377, 306, 386, 313]}
{"merge_info": [35, -1, 0, -1], "bbox_info": [0, 315, 28, 322]}
{"merge_info": [35, -1, 1, -1], "bbox_info": [101, 315, 110, 322]}
{"merge_info": [35, -1, 2, -1], "bbox_info": [156, 315, 165, 322]}
{"merge_info": [35, -1, 3, -1], "bbox_info": [211, 315, 220, 322]}
{"merge_info": [35, -1, 4, -1], "bbox_info": [266, 315, 275, 322]}
{"merge_info": [35, -1, 5, -1], "bbox_info": [322, 315, 330, 322]}
{"merge_info": [35, -1, 6, -1], "bbox_info": [377, 315, 386, 322]}
{"merge_info": [36, -1, 0, -1], "bbox_info": [0, 324, 15, 331]}
{"merge_info": [36, -1, 1, -1], "bbox_info": [101, 324, 110, 331]}
{"merge_info": [36, -1, 2, -1], "bbox_info": [156, 324, 165, 331]}
{"merge_info": [36, -1, 3, -1], "bbox_info": [211, 324, 220, 331]}
{"merge_info": [36, -1, 4, -1], "bbox_info": [266, 324, 275, 331]}
{"merge_info": [36, -1, 5, -1], "bbox_info": [322, 324, 330, 331]}
{"merge_info": [36, -1, 6, -1], "bbox_info": [377, 324, 386, 331]}
{"merge_info": [37, -1, 0, -1], "bbox_info": [0, 333, 21, 340]}
{"merge_info": [37, -1, 1, -1], "bbox_info": [101, 333, 110, 340]}
{"merge_info": [37, -1, 2, -1], "bbox_info": [156, 333, 165, 340]}
{"merge_info": [37, -1, 3, -1], "bbox_info": [211, 333, 220, 340]}
{"merge_info": [37, -1, 4, -1], "bbox_info": [266, 333, 275, 340]}
{"merge_info": [37, -1, 5, -1], "bbox_info": [322, 333, 330, 340]}
{"merge_info": [37, -1, 6, -1], "bbox_info": [377, 333, 386, 340]}
{"merge_info": [38, -1, 0, -1], "bbox_info": [0, 342, 27, 349]}
{"merge_info": [38, -1, 1, -1], "bbox_info": [101, 342, 110, 349]}
{"merge_info": [38, -1, 2, -1], "bbox_info": [156, 342, 165, 349]}
{"merge_info": [38, -1, 3, -1], "bbox_info": [211, 342, 220, 349]}
{"merge_info": [38, -1, 4, -1], "bbox_info": [266, 342, 275, 349]}
{"merge_info": [38, -1, 5, -1], "bbox_info": [322, 342, 330, 349]}
{"merge_info": [38, -1, 6, -1], "bbox_info": [377, 342, 386, 349]}
{"merge_info": [39, -1, 0, -1], "bbox_info": [0, 352, 30, 359]}
{"merge_info": [39, -1, 1, -1], "bbox_info": [101, 352, 110, 359]}
{"merge_info": [39, -1, 2, -1], "bbox_info": [156, 352, 165, 359]}
{"merge_info": [39, -1, 3, -1], "bbox_info": [211, 352, 220, 359]}
{"merge_info": [39, -1, 4, -1], "bbox_info": [266, 352, 275, 359]}
{"merge_info": [39, -1, 5, -1], "bbox_info": [322, 352, 330, 359]}
{"merge_info": [39, -1, 6, -1], "bbox_info": [377, 352, 386, 359]}
{"merge_info": [40, -1, 0, -1], "bbox_info": [0, 361, 18, 368]}
{"merge_info": [40, -1, 1, -1], "bbox_info": [101, 361, 110, 368]}
{"merge_info": [40, -1, 2, -1], "bbox_info": [156, 361, 165, 368]}
{"merge_info": [40, -1, 3, -1], "bbox_info": [211, 361, 220, 368]}
{"merge_info": [40, -1, 4, -1], "bbox_info": [266, 361, 275, 368]}
{"merge_info": [40, -1, 5, -1], "bbox_info": [322, 361, 330, 368]}
{"merge_info": [40, -1, 6, -1], "bbox_info": [377, 361, 386, 368]}
{"merge_info": [41, -1, 0, -1], "bbox_info": [0, 370, 38, 377]}
{"merge_info": [41, -1, 1, -1], "bbox_info": [101, 370, 110, 377]}
{"merge_info": [41, -1, 2, -1], "bbox_info": [156, 370, 165, 377]}
{"merge_info": [41, -1, 3, -1], "bbox_info": [211, 370, 220, 377]}
{"merge_info": [41, -1, 4, -1], "bbox_info": [266, 370, 275, 377]}
{"merge_info": [41, -1, 5, -1], "bbox_info": [322, 370, 330, 377]}
{"merge_info": [41, -1, 6, -1], "bbox_info": [377, 370, 386, 377]}
{"merge_info": [42, -1, 0, -1], "bbox_info": [0, 379, 21, 386]}
{"merge_info": [42, -1, 1, -1], "bbox_info": [101, 379, 110, 386]}
{"merge_info": [42, -1, 2, -1], "bbox_info": [156, 379, 165, 386]}
{"merge_info": [42, -1, 3, -1], "bbox_info": [211, 379, 220, 386]}
{"merge_info": [42, -1, 4, -1], "bbox_info": [266, 379, 275, 386]}
{"merge_info": [42, -1, 5, -1], "bbox_info": [322, 379, 330, 386]}
{"merge_info": [42, -1, 6, -1], "bbox_info": [377, 379, 386, 386]}
{"merge_info": [43, -1, 0, -1], "bbox_info": [0, 392, 16, 399]}
{"merge_info": [43, -1, 1, -1], "bbox_info": [94, 392, 110, 399]}
{"merge_info": [43, -1, 2, -1], "bbox_info": [149, 392, 165, 399]}
{"merge_info": [43, -1, 3, -1], "bbox_info": [204, 392, 220, 399]}
{"merge_info": [43, -1, 4, -1], "bbox_info": [259, 392, 275, 399]}
{"merge_info": [43, -1, 5, -1], "bbox_info": [315, 392, 330, 399]}
{"merge_info": [43, -1, 6, -1], "bbox_info": [370, 392, 386, 399]}
