{"merge_info": [0, -1, 0, -1], "bbox_info": [98, 25, 139, 36]}
{"merge_info": [0, -1, 1, -1], "bbox_info": [249, 0, 304, 35]}
{"merge_info": [0, -1, 2, -1], "bbox_info": [317, 24, 344, 35]}
{"merge_info": [0, -1, 3, -1], "bbox_info": [367, 24, 376, 35]}
{"merge_info": [0, -1, 4, -1], "bbox_info": [399, 11, 429, 35]}
{"merge_info": [0, -1, 5, -1], "bbox_info": [444, 11, 474, 36]}
{"merge_info": [1, -1, 0, 5], "bbox_info": [0, 39, 175, 50]}
{"merge_info": [2, -1, 0, -1], "bbox_info": [9, 53, 96, 64]}
{"merge_info": [2, -1, 3, -1], "bbox_info": [366, 57, 377, 65]}
{"merge_info": [2, -1, 4, -1], "bbox_info": [408, 57, 420, 65]}
{"merge_info": [2, -1, 5, -1], "bbox_info": [453, 57, 464, 65]}
{"merge_info": [3, -1, 0, -1], "bbox_info": [9, 66, 185, 77]}
{"merge_info": [3, -1, 1, -1], "bbox_info": [267, 67, 286, 78]}
{"merge_info": [3, -1, 3, -1], "bbox_info": [366, 70, 377, 78]}
{"merge_info": [3, -1, 4, -1], "bbox_info": [408, 70, 420, 78]}
{"merge_info": [3, -1, 5, -1], "bbox_info": [453, 70, 464, 78]}
{"merge_info": [4, -1, 0, -1], "bbox_info": [9, 80, 184, 91]}
{"merge_info": [4, -1, 1, -1], "bbox_info": [267, 80, 286, 91]}
{"merge_info": [4, -1, 2, -1], "bbox_info": [321, 80, 340, 91]}
{"merge_info": [4, -1, 3, -1], "bbox_info": [366, 84, 377, 92]}
{"merge_info": [4, -1, 4, -1], "bbox_info": [408, 84, 420, 92]}
{"merge_info": [4, -1, 5, -1], "bbox_info": [453, 84, 464, 92]}
{"merge_info": [5, -1, 0, -1], "bbox_info": [9, 93, 73, 104]}
{"merge_info": [5, -1, 1, -1], "bbox_info": [267, 93, 286, 104]}
{"merge_info": [5, -1, 4, -1], "bbox_info": [408, 97, 420, 105]}
{"merge_info": [5, -1, 5, -1], "bbox_info": [453, 97, 464, 105]}
{"merge_info": [6, -1, 0, -1], "bbox_info": [9, 107, 235, 118]}
{"merge_info": [6, -1, 1, -1], "bbox_info": [267, 107, 286, 118]}
{"merge_info": [6, -1, 2, -1], "bbox_info": [321, 107, 340, 118]}
{"merge_info": [6, -1, 4, -1], "bbox_info": [408, 110, 420, 118]}
{"merge_info": [6, -1, 5, -1], "bbox_info": [453, 110, 464, 118]}
{"merge_info": [7, -1, 0, -1], "bbox_info": [9, 120, 144, 131]}
{"merge_info": [7, -1, 1, -1], "bbox_info": [267, 120, 286, 131]}
{"merge_info": [8, -1, 0, -1], "bbox_info": [9, 133, 161, 144]}
{"merge_info": [8, -1, 1, -1], "bbox_info": [267, 134, 286, 145]}
{"merge_info": [9, -1, 0, -1], "bbox_info": [9, 147, 81, 158]}
{"merge_info": [9, -1, 5, -1], "bbox_info": [453, 151, 464, 159]}
{"merge_info": [10, -1, 0, -1], "bbox_info": [9, 160, 136, 171]}
{"merge_info": [10, -1, 4, -1], "bbox_info": [404, 160, 424, 172]}
{"merge_info": [10, -1, 5, -1], "bbox_info": [453, 164, 464, 172]}
{"merge_info": [11, -1, 0, -1], "bbox_info": [9, 174, 135, 185]}
{"merge_info": [11, -1, 1, -1], "bbox_info": [267, 174, 286, 185]}
{"merge_info": [11, -1, 5, -1], "bbox_info": [453, 177, 464, 185]}
{"merge_info": [12, -1, 0, -1], "bbox_info": [9, 187, 171, 198]}
{"merge_info": [12, -1, 1, -1], "bbox_info": [271, 191, 282, 199]}
{"merge_info": [12, -1, 2, -1], "bbox_info": [325, 191, 336, 199]}
{"merge_info": [12, -1, 5, -1], "bbox_info": [453, 191, 464, 199]}
{"merge_info": [13, -1, 0, -1], "bbox_info": [9, 200, 108, 211]}
{"merge_info": [13, -1, 1, -1], "bbox_info": [271, 204, 282, 212]}
{"merge_info": [13, -1, 2, -1], "bbox_info": [325, 204, 336, 212]}
{"merge_info": [13, -1, 5, -1], "bbox_info": [453, 204, 464, 212]}
{"merge_info": [14, -1, 0, -1], "bbox_info": [9, 214, 148, 225]}
{"merge_info": [14, -1, 1, -1], "bbox_info": [271, 218, 282, 226]}
{"merge_info": [14, -1, 2, -1], "bbox_info": [325, 218, 336, 226]}
{"merge_info": [14, -1, 3, -1], "bbox_info": [366, 218, 377, 226]}
{"merge_info": [14, -1, 5, -1], "bbox_info": [453, 218, 464, 226]}
{"merge_info": [15, -1, 0, -1], "bbox_info": [9, 227, 116, 238]}
{"merge_info": [15, -1, 1, -1], "bbox_info": [271, 231, 282, 239]}
{"merge_info": [15, -1, 2, -1], "bbox_info": [325, 231, 336, 239]}
{"merge_info": [15, -1, 3, -1], "bbox_info": [366, 231, 377, 239]}
{"merge_info": [15, -1, 5, -1], "bbox_info": [453, 231, 464, 239]}
{"merge_info": [16, -1, 0, -1], "bbox_info": [9, 241, 151, 252]}
{"merge_info": [16, -1, 1, -1], "bbox_info": [271, 244, 282, 252]}
{"merge_info": [16, -1, 2, -1], "bbox_info": [325, 244, 336, 252]}
{"merge_info": [16, -1, 3, -1], "bbox_info": [366, 244, 377, 252]}
{"merge_info": [16, -1, 5, -1], "bbox_info": [453, 244, 464, 252]}
{"merge_info": [17, -1, 0, -1], "bbox_info": [9, 254, 87, 265]}
{"merge_info": [17, -1, 1, -1], "bbox_info": [271, 258, 282, 266]}
{"merge_info": [17, -1, 2, -1], "bbox_info": [325, 258, 336, 266]}
{"merge_info": [17, -1, 3, -1], "bbox_info": [366, 258, 377, 266]}
{"merge_info": [18, -1, 0, -1], "bbox_info": [9, 267, 114, 278]}
{"merge_info": [18, -1, 1, -1], "bbox_info": [271, 271, 282, 279]}
{"merge_info": [18, -1, 2, -1], "bbox_info": [325, 271, 336, 279]}
{"merge_info": [18, -1, 3, -1], "bbox_info": [366, 271, 377, 279]}
{"merge_info": [18, -1, 5, -1], "bbox_info": [453, 271, 464, 279]}
{"merge_info": [19, -1, 0, 5], "bbox_info": [0, 282, 86, 293]}
{"merge_info": [20, -1, 0, -1], "bbox_info": [9, 296, 141, 307]}
{"merge_info": [20, -1, 5, -1], "bbox_info": [453, 299, 464, 307]}
{"merge_info": [21, -1, 0, -1], "bbox_info": [9, 309, 215, 320]}
{"merge_info": [21, -1, 3, -1], "bbox_info": [362, 309, 381, 320]}
{"merge_info": [22, -1, 0, 5], "bbox_info": [0, 323, 25, 334]}
{"merge_info": [23, -1, 0, -1], "bbox_info": [9, 337, 177, 348]}
{"merge_info": [23, -1, 3, -1], "bbox_info": [366, 341, 377, 349]}
{"merge_info": [23, -1, 4, -1], "bbox_info": [408, 341, 420, 349]}
{"merge_info": [23, -1, 5, -1], "bbox_info": [453, 341, 464, 349]}
{"merge_info": [24, -1, 0, -1], "bbox_info": [9, 351, 124, 362]}
{"merge_info": [24, -1, 1, -1], "bbox_info": [267, 351, 286, 362]}
{"merge_info": [25, -1, 0, -1], "bbox_info": [9, 364, 142, 375]}
{"merge_info": [25, -1, 1, -1], "bbox_info": [271, 368, 282, 376]}
{"merge_info": [25, -1, 2, -1], "bbox_info": [325, 368, 336, 376]}
{"merge_info": [25, -1, 5, -1], "bbox_info": [453, 368, 464, 376]}
{"merge_info": [26, -1, 0, -1], "bbox_info": [9, 378, 116, 389]}
{"merge_info": [26, -1, 1, -1], "bbox_info": [271, 381, 282, 389]}
{"merge_info": [26, -1, 2, -1], "bbox_info": [325, 381, 336, 389]}
{"merge_info": [26, -1, 5, -1], "bbox_info": [453, 381, 464, 389]}
{"merge_info": [27, -1, 0, -1], "bbox_info": [9, 391, 95, 402]}
{"merge_info": [27, -1, 1, -1], "bbox_info": [271, 395, 282, 403]}
{"merge_info": [27, -1, 2, -1], "bbox_info": [325, 395, 336, 403]}
{"merge_info": [27, -1, 3, -1], "bbox_info": [366, 395, 377, 403]}
{"merge_info": [28, -1, 0, 5], "bbox_info": [0, 405, 95, 416]}
{"merge_info": [29, -1, 0, -1], "bbox_info": [9, 419, 121, 430]}
{"merge_info": [29, -1, 1, -1], "bbox_info": [271, 423, 282, 431]}
{"merge_info": [29, -1, 2, -1], "bbox_info": [325, 423, 336, 431]}
{"merge_info": [29, -1, 5, -1], "bbox_info": [453, 423, 464, 431]}
{"merge_info": [30, -1, 0, -1], "bbox_info": [9, 433, 122, 444]}
{"merge_info": [30, -1, 1, -1], "bbox_info": [271, 436, 282, 445]}
{"merge_info": [30, -1, 2, -1], "bbox_info": [325, 436, 336, 445]}
{"merge_info": [30, -1, 5, -1], "bbox_info": [447, 433, 470, 444]}
{"merge_info": [31, -1, 0, -1], "bbox_info": [9, 446, 144, 457]}
{"merge_info": [31, -1, 1, -1], "bbox_info": [271, 450, 282, 458]}
{"merge_info": [31, -1, 2, -1], "bbox_info": [325, 450, 336, 458]}
{"merge_info": [32, -1, 0, -1], "bbox_info": [9, 460, 66, 471]}
{"merge_info": [32, -1, 1, -1], "bbox_info": [271, 463, 282, 471]}
{"merge_info": [32, -1, 2, -1], "bbox_info": [325, 463, 336, 471]}
{"merge_info": [32, -1, 3, -1], "bbox_info": [360, 460, 383, 471]}
{"merge_info": [33, -1, 0, -1], "bbox_info": [9, 473, 60, 484]}
{"merge_info": [33, -1, 1, -1], "bbox_info": [271, 477, 282, 485]}
{"merge_info": [33, -1, 2, -1], "bbox_info": [325, 477, 336, 485]}
{"merge_info": [33, -1, 3, -1], "bbox_info": [366, 477, 377, 485]}
{"merge_info": [33, -1, 4, -1], "bbox_info": [408, 477, 420, 485]}
{"merge_info": [34, -1, 0, -1], "bbox_info": [9, 486, 141, 497]}
{"merge_info": [34, -1, 1, -1], "bbox_info": [271, 490, 282, 498]}
{"merge_info": [34, -1, 2, -1], "bbox_info": [325, 490, 336, 498]}
{"merge_info": [34, -1, 3, -1], "bbox_info": [366, 490, 377, 498]}
{"merge_info": [34, -1, 4, -1], "bbox_info": [408, 490, 420, 498]}
{"merge_info": [35, -1, 0, -1], "bbox_info": [9, 500, 161, 511]}
{"merge_info": [35, -1, 1, -1], "bbox_info": [271, 503, 282, 511]}
{"merge_info": [35, -1, 2, -1], "bbox_info": [325, 503, 336, 511]}
{"merge_info": [35, -1, 5, -1], "bbox_info": [453, 503, 464, 511]}
